{
  "courses": [
    {
      "id": 0,
      "name": "産業経済",
      "required": [
        "産業経済論Ａ"
      ],
      "elective": [
        "ミクロ経済学Ａ",
        "ミクロ経済学Ｂ",
        "マクロ経済学Ａ",
        "マクロ経済学Ｂ",
        "計量経済学の基礎A",
        "計量経済学の基礎B",
        "産業経済論Ｂ",
        "経済政策論Ａ",
        "経済政策論Ｂ",
        "労働経済論Ａ",
        "労働経済論Ｂ",
        "金融論Ａ",
        "金融論Ｂ",
        "日本経済論Ａ",
        "日本経済論Ｂ",
        "財政学Ａ",
        "財政学Ｂ",
        "情報経済論Ａ",
        "情報経済論Ｂ",
        "農業経済論Ａ",
        "農業経済論Ｂ",
        "開発経済学A",
        "開発経済学B",
        "経済学史Ａ",
        "経済学史Ｂ"
      ],
      "course_subjects": [
        "データ処理入門",
        "経済数学",
        "計量経済学Ⅰ",
        "計量経済学Ⅱ",
        "環境経済学",
        "資源経済論",
        "地域経済論Ａ",
        "地域経済論Ｂ",
        "国際経済論Ａ",
        "国際経済論Ｂ",
        "国際金融論Ａ",
        "国際金融論Ｂ",
        "行動経済学A",
        "行動経済学B",
        "ファイナンスＡ",
        "ファイナンスＢ",
        "日本経済史Ａ",
        "日本経済史Ｂ",
        "社会思想史Ａ",
        "社会思想史Ｂ",
        "西洋経済史Ａ",
        "西洋経済史Ｂ"
      ],
      "other_subjects": [
        "Microeconomics in English",
        "Macroeconomics in English",
        "公共経済学概論",
        "公共経済学特論",
        "Global Topics A",
        "地域経済論Ｃ",
        "国際法",
        "地方財政論Ａ",
        "地方財政論Ｂ",
        "租税論Ａ",
        "租税論Ｂ",
        "福祉経済論Ａ",
        "福祉経済論Ｂ",
        "社会保障論Ａ",
        "社会保障論Ｂ",
        "Global Topics B",
        "都市経済論Ａ",
        "都市経済論Ｂ",
        "地域文化論"
      ]
    },
    {
      "id": 1,
      "name": "公共経済",
      "required": [
        "財政学Ａ"
      ],
      "elective": [
        "ミクロ経済学Ａ",
        "ミクロ経済学Ｂ",
        "マクロ経済学Ａ",
        "マクロ経済学Ｂ",
        "計量経済学の基礎A",
        "計量経済学の基礎B",
        "経済政策論Ａ",
        "経済政策論Ｂ",
        "金融論Ａ",
        "金融論Ｂ",
        "財政学Ｂ",
        "経済学史Ａ",
        "経済学史Ｂ",
        "環境経済学",
        "資源経済論",
        "公共経済学概論",
        "公共経済学特論",
        "地方財政論Ａ",
        "地方財政論Ｂ",
        "租税論Ａ",
        "租税論Ｂ",
        "福祉経済論Ａ",
        "福祉経済論Ｂ",
        "社会保障論Ａ",
        "社会保障論Ｂ"
      ],
      "course_subjects": [
        "労働経済論Ａ",
        "労働経済論Ｂ",
        "日本経済論Ａ",
        "日本経済論Ｂ",
        "情報経済論Ａ",
        "情報経済論Ｂ",
        "データ処理入門",
        "経済数学",
        "計量経済学Ⅰ",
        "計量経済学Ⅱ",
        "地域経済論Ａ",
        "地域経済論Ｂ",
        "国際経済論Ａ",
        "国際経済論Ｂ",
        "国際金融論Ａ",
        "国際金融論Ｂ",
        "行動経済学A",
        "行動経済学B",
        "日本経済史Ａ",
        "日本経済史Ｂ",
        "社会思想史Ａ",
        "社会思想史Ｂ",
        "西洋経済史Ａ",
        "西洋経済史Ｂ",
        "都市経済論Ａ",
        "都市経済論Ｂ",
        "地域文化論"
      ],
      "other_subjects": [
        "産業経済論Ａ",
        "産業経済論Ｂ",
        "農業経済論Ａ",
        "農業経済論Ｂ",
        "開発経済学A",
        "開発経済学B",
        "ファイナンスＡ",
        "ファイナンスＢ",
        "Microeconomics in English",
        "Macroeconomics in English",
        "Global Topics A",
        "地域経済論Ｃ",
        "国際法",
        "Global Topics B"
      ]
    },
    {
      "id": 2,
      "name": "スポーツ経済",
      "required": [
        "スポーツ経済学入門"
      ],
      "elective": [
        "ミクロ経済学Ａ",
        "ミクロ経済学Ｂ",
        "マクロ経済学Ａ",
        "マクロ経済学Ｂ",
        "産業経済論Ａ",
        "産業経済論Ｂ",
        "経済政策論Ａ",
        "経済政策論Ｂ",
        "労働経済論Ａ",
        "労働経済論Ｂ",
        "金融論Ａ",
        "金融論Ｂ",
        "財政学Ａ",
        "財政学Ｂ",
        "経済学史Ａ",
        "経済学史Ｂ",
        "スポーツ経済学A",
        "スポーツ経済学B",
        "スポーツ産業論Ａ",
        "スポーツ産業論Ｂ",
        "スポーツ政策論Ａ",
        "スポーツ政策論Ｂ",
        "スポーツビジネス論",
        "スポーツファイナンスＡ",
        "スポーツファイナンスＢ",
        "スポーツマーケティング論",
        "スポーツ報道論",
        "スポーツマネジメント論Ａ",
        "スポーツマネジメント論Ｂ",
        "スポーツ法学"
      ],
      "course_subjects": [
        "計量経済学の基礎A",
        "計量経済学の基礎B",
        "日本経済論Ａ",
        "日本経済論Ｂ",
        "データ処理入門",
        "経済数学",
        "計量経済学Ⅰ",
        "計量経済学Ⅱ",
        "環境経済学",
        "資源経済論",
        "地域経済論Ａ",
        "地域経済論Ｂ",
        "国際経済論Ａ",
        "国際経済論Ｂ",
        "国際金融論Ａ",
        "国際金融論Ｂ",
        "行動経済学A",
        "行動経済学B",
        "日本経済史Ａ",
        "日本経済史Ｂ",
        "社会思想史Ａ",
        "社会思想史Ｂ",
        "西洋経済史Ａ",
        "西洋経済史Ｂ",
        "公共経済学概論",
        "公共経済学特論",
        "福祉経済論Ａ",
        "福祉経済論Ｂ"
      ],
      "other_subjects": [
        "情報経済論Ａ",
        "情報経済論Ｂ",
        "農業経済論Ａ",
        "農業経済論Ｂ",
        "開発経済学A",
        "開発経済学B",
        "ファイナンスＡ",
        "ファイナンスＢ",
        "Microeconomics in English",
        "Macroeconomics in English",
        "Global Topics A",
        "地域経済論Ｃ",
        "国際法",
        "地方財政論Ａ",
        "地方財政論Ｂ",
        "租税論Ａ",
        "租税論Ｂ",
        "社会保障論Ａ",
        "社会保障論Ｂ",
        "Global Topics B",
        "都市経済論Ａ",
        "都市経済論Ｂ",
        "地域文化論"
      ]
    },
    {
      "id": 3,
      "name": "グローバル・エコノミー",
      "required": [
        "国際経済論Ａ"
      ],
      "elective": [
        "ミクロ経済学Ａ",
        "ミクロ経済学Ｂ",
        "マクロ経済学Ａ",
        "マクロ経済学Ｂ",
        "計量経済学の基礎A",
        "計量経済学の基礎B",
        "経済政策論Ａ",
        "経済政策論Ｂ",
        "金融論Ａ",
        "金融論Ｂ",
        "日本経済論Ａ",
        "日本経済論Ｂ",
        "財政学Ａ",
        "財政学Ｂ",
        "経済学史Ａ",
        "経済学史Ｂ",
        "地域経済論Ａ",
        "地域経済論Ｂ",
        "国際経済論Ｂ",
        "国際金融論Ａ",
        "国際金融論Ｂ",
        "西洋経済史Ａ",
        "西洋経済史Ｂ",
        "Microeconomics in English",
        "Macroeconomics in English",
        "Global Topics A",
        "Global Topics B"
      ],
      "course_subjects": [
        "産業経済論Ａ",
        "産業経済論Ｂ",
        "情報経済論Ａ",
        "情報経済論Ｂ",
        "開発経済学A",
        "開発経済学B",
        "データ処理入門",
        "経済数学",
        "計量経済学Ⅰ",
        "計量経済学Ⅱ",
        "環境経済学",
        "資源経済論",
        "行動経済学A",
        "行動経済学B",
        "ファイナンスＡ",
        "ファイナンスＢ",
        "日本経済史Ａ",
        "日本経済史Ｂ",
        "社会思想史Ａ",
        "社会思想史Ｂ",
        "地域経済論Ｃ",
        "国際法"
      ],
      "other_subjects": [
        "労働経済論Ａ",
        "労働経済論Ｂ",
        "農業経済論Ａ",
        "農業経済論Ｂ",
        "公共経済学概論",
        "公共経済学特論",
        "地方財政論Ａ",
        "地方財政論Ｂ",
        "租税論Ａ",
        "租税論Ｂ",
        "福祉経済論Ａ",
        "福祉経済論Ｂ",
        "社会保障論Ａ",
        "社会保障論Ｂ",
        "都市経済論Ａ",
        "都市経済論Ｂ",
        "地域文化論"
      ]
    }
  ],
  "basics": [
    "経済入門",
    "経済理論Ａ",
    "経済理論Ｂ",
    "経済史概論"
  ],
  "freshman_seminar": [
    "フレッシュマンゼミナールＡ",
    "フレッシュマンゼミナールＢ"
  ],
  "other_seminar": [
    "基礎ゼミナールＡ",
    "基礎ゼミナールＢ",
    "専門ゼミナールⅠ",
    "専門ゼミナールⅡ",
    "専門ゼミナールⅢ",
    "専門ゼミナールⅣ"
  ],
  "other_categories": [
    "初年次教育",
    "教養",
    "言語",
    "実務基礎",
    "関連科目　スポーツサイエンス",
    "関連科目　特別講義",
    "関連科目　ワークショップ",
    "関連科目　研修・留学",
    "他学科履修科目",
    "学科科目以外の認定科目",
    "実践課題研究Ⅰ・Ⅱ・Ⅲ"
  ]
}